r00parser_docs/main.py
r00parser_docs/parsers.py
r00parser_docs-0.1.0.dist-info/METADATA
r00parser_docs-0.1.0.dist-info/WHEEL
r00parser_docs-0.1.0.dist-info/entry_points.txt
r00parser_docs-0.1.0.dist-info/RECORD
